entityextractiondemo/__init__.py
entityextractiondemo/extraction.py
entityextractiondemo/OBOL_SAMPLE.pdf
entityextractiondemo/PDF/OBOL_SAMPLE.pdf
entityextractiondemo/PDF/SWB_SAMPLE.pdf
entityextractiondemo/SWB_SAMPLE.pdf
entityextractiondemo/utils.py
entityextractiondemo-0.1.0.dist-info/METADATA
entityextractiondemo-0.1.0.dist-info/WHEEL
entityextractiondemo-0.1.0.dist-info/RECORD
