Metadata-Version: 2.1
Name: entityextractiondemo
Version: 0.1.0
Summary: 
Author: Sayantan Das
Author-email: sayantan.das013@gmail.com
Requires-Python: >=3.12,<4.0
Classifier: Programming Language :: Python :: 3
Classifier: Programming Language :: Python :: 3.12
Requires-Dist: google-generativeai (>=0.5.0,<0.6.0)
Requires-Dist: install (>=1.3.5,<2.0.0)
Requires-Dist: langchain (>=0.1.16,<0.2.0)
Requires-Dist: pip (>=24.0,<25.0)
Requires-Dist: pypdf (>=4.2.0,<5.0.0)
Requires-Dist: pypdf2 (>=3.0.1,<4.0.0)
